pywekaclassifiers/__init__.py
pywekaclassifiers/arff.py
pywekaclassifiers/classifiers.py
pywekaclassifiers/tests.py
pywekaclassifiers/fixtures/abalone-query-bad.arff
pywekaclassifiers/fixtures/abalone-query.arff
pywekaclassifiers/fixtures/abalone-train.arff
pywekaclassifiers/fixtures/abalone.arff
pywekaclassifiers/fixtures/updateable-train-1.arff
pywekaclassifiers/fixtures/updateable-train-2.arff
pywekaclassifiers-0.0.3.dist-info/LICENSE
pywekaclassifiers-0.0.3.dist-info/METADATA
pywekaclassifiers-0.0.3.dist-info/WHEEL
pywekaclassifiers-0.0.3.dist-info/top_level.txt
pywekaclassifiers-0.0.3.dist-info/RECORD
