Metadata-Version: 2.1
Name: pywekaclassifiers
Version: 0.0.3
Summary: A Python wrapper for the Weka data mining library.
Home-page: https://github.com/Nicusor97/PyWekaClassifiers.git
Author: Picatureanu Nicusor
Author-email: nicolaepicatureanu@gmail.com
License: MIT License
Platform: OS Independent
Classifier: Programming Language :: Python
Classifier: Programming Language :: Python :: 2.7
Classifier: Programming Language :: Python :: 3.3
Classifier: Programming Language :: Python :: 3.4
Classifier: Programming Language :: Python :: 3.5
Classifier: Programming Language :: Python :: 3.6
Classifier: Development Status :: 5 - Production/Stable
Classifier: Operating System :: OS Independent
Classifier: Topic :: Software Development :: Libraries :: Python Modules
Classifier: Topic :: Text Processing :: General
Requires-Dist: six (>=1.11.0)
Requires-Dist: python-dateutil (>=2.6.1)
Requires-Dist: Sphinx (==1.4.2)
